pocode/__init__.py
pocode/api/__init__.py
pocode/api/color.py
pocode/api/lifecycle.py
pocode/api/line.py
pocode/lib/__init__.py
tests/__init__.py
tests/test_pocode.py
pocode-0.0.3.dist-info/LICENSE
pocode-0.0.3.dist-info/METADATA
pocode-0.0.3.dist-info/WHEEL
pocode-0.0.3.dist-info/top_level.txt
pocode-0.0.3.dist-info/RECORD
