Metadata-Version: 2.1
Name: pocode
Version: 0.0.3
Summary: pip install pocode
Home-page: https://www.python-office.com/
Author: CoderWanFeng
Author-email: 1957875073@qq.com
License: MIT
Project-URL: Bug Tracker, https://github.com/CoderWanFeng/pocode/issues
Project-URL: Documentation, https://github.com/CoderWanFeng/pocode/blob/master/README.md
Project-URL: Source Code, https://github.com/CoderWanFeng/pocode
Platform: any
Requires-Python: >=3.6
License-File: LICENSE
Requires-Dist: colorama
